rpmrh/__init__.py
rpmrh/__main__.py
rpmrh/exception.py
rpmrh/rpm.py
rpmrh/cli/__init__.py
rpmrh/cli/command.py
rpmrh/cli/tooling.py
rpmrh/conf.d/cbs.service.toml
rpmrh/conf.d/config.toml
rpmrh/conf.d/sclo-sig.phase.toml
rpmrh/configuration/__init__.py
rpmrh/configuration/_loading.py
rpmrh/configuration/_validation.py
rpmrh/configuration/phase.py
rpmrh/configuration/runtime.py
rpmrh/configuration/service.py
rpmrh/service/__init__.py
rpmrh/service/abc.py
rpmrh/service/jenkins.py
rpmrh/service/koji.py
rpmrh/service/dnf/__init__.py
rpmrh/service/dnf/_compat.py
rpmrh/service/dnf/interface.py
rpmrh/util/__init__.py
rpmrh/util/importlib.py
rpmrh/util/iterable.py
rpmrh/util/logging.py
rpmrh/util/net.py
rpmrh-0.7.2.dist-info/LICENSE
rpmrh-0.7.2.dist-info/METADATA
rpmrh-0.7.2.dist-info/WHEEL
rpmrh-0.7.2.dist-info/entry_points.txt
rpmrh-0.7.2.dist-info/top_level.txt
rpmrh-0.7.2.dist-info/RECORD
