Metadata-Version: 2.1
Name: rpmrh
Version: 0.7.2
Summary: An automation tool for rebuilding RPMs and Software Collections
Home-page: https://github.com/khardix/rpm-rebuild-helper
Author: Jan Staněk
Author-email: jstanek@redhat.com
License: GNU General Public License version 3 or later
Keywords: rpm,scl,softwarecollections,rebuilding
Platform: Linux
Classifier: Development Status :: 3 - Alpha
Classifier: Intended Audience :: Developers
Classifier: Topic :: Software Development :: Build Tools
Classifier: License :: OSI Approved :: GNU General Public License v3 or later (GPLv3+)
Classifier: Programming Language :: Python :: 3
Classifier: Programming Language :: Python :: 3 :: Only
Classifier: Programming Language :: Python :: 3.6
Classifier: Programming Language :: Python :: 3.7
Classifier: Programming Language :: Python :: Implementation :: CPython
Requires-Dist: attrs (>=17)
Requires-Dist: cerberus
Requires-Dist: click
Requires-Dist: click-log
Requires-Dist: python-jenkins
Requires-Dist: pyxdg
Requires-Dist: requests
Requires-Dist: requests-file
Requires-Dist: ruamel.yaml (~=0.15)
Requires-Dist: toml
Provides-Extra: dev
Requires-Dist: PyTrie ; extra == 'dev'
Requires-Dist: betamax ; extra == 'dev'
Requires-Dist: ipython ; extra == 'dev'
Requires-Dist: pyfakefs ; extra == 'dev'
Requires-Dist: pytest ; extra == 'dev'
Requires-Dist: pytest-mock ; extra == 'dev'
Requires-Dist: sphinx ; extra == 'dev'
Requires-Dist: sphinx-autobuild ; extra == 'dev'
Provides-Extra: system
Requires-Dist: rpm (>=4.11) ; extra == 'system'
Requires-Dist: dnf (>=4.1) ; extra == 'system'
Requires-Dist: koji (>=1.16) ; extra == 'system'
Requires-Dist: createrepo-c ; extra == 'system'
